chemviewer/__init__.py
chemviewer/core.py
chemviewer/run.py
chemviewer/standalone.py
chemviewer/webserver.py
chemviewer/static/css.css
chemviewer/static/main.js
chemviewer/templates/index.html
tests/__init__.py
chemviewer-0.1.2.dist-info/LICENSE
chemviewer-0.1.2.dist-info/METADATA
chemviewer-0.1.2.dist-info/WHEEL
chemviewer-0.1.2.dist-info/entry_points.txt
chemviewer-0.1.2.dist-info/top_level.txt
chemviewer-0.1.2.dist-info/RECORD
