Metadata-Version: 2.1
Name: chemviewer
Version: 0.1.2
Summary: A web based application to view 2D structures in a table
Home-page: https://github.com/zealseeker/chemviewer
Author: Hongbin Yang
Author-email: yanyanghong@163.com
License: UNKNOWN
Platform: UNKNOWN
Classifier: Programming Language :: Python :: 3
Classifier: License :: OSI Approved :: MIT License
Classifier: Operating System :: OS Independent
